cli_commons/__init__.py
cli_commons/cli_core.py
cli_commons/colors.py
cli_commons/command_base.py
cli_commons/directories.py
cli_commons/file_ops.py
cli_commons/loader.py
cli_commons/logger.py
cli_commons/parser.py
cli_commons/py.typed
cli_standard_kit-1.0.4.dist-info/licenses/LICENSE
cli_standard_kit-1.0.4.dist-info/METADATA
cli_standard_kit-1.0.4.dist-info/WHEEL
cli_standard_kit-1.0.4.dist-info/top_level.txt
cli_standard_kit-1.0.4.dist-info/RECORD
