Metadata-Version: 2.4
Name: cli-standard-kit
Version: 1.0.4
Summary: Reusable CLI framework and utilities for consistent command-line interfaces
Author-email: Cenk Kabahasanoglu <me@c3nk.com>
Project-URL: Homepage, https://github.com/c3nk/cli-standard-kit
Project-URL: Documentation, https://github.com/c3nk/cli-standard-kit#readme
Project-URL: Repository, https://github.com/c3nk/cli-standard-kit.git
Project-URL: Issues, https://github.com/c3nk/cli-standard-kit/issues
Keywords: cli,command-line,framework,utilities,colors,logging,batch-processing,argparse
Classifier: Development Status :: 4 - Beta
Classifier: Intended Audience :: Developers
Classifier: License :: OSI Approved :: MIT License
Classifier: Programming Language :: Python :: 3
Classifier: Programming Language :: Python :: 3.9
Classifier: Programming Language :: Python :: 3.10
Classifier: Programming Language :: Python :: 3.11
Classifier: Programming Language :: Python :: 3.12
Classifier: Topic :: Software Development :: Libraries :: Python Modules
Classifier: Topic :: System :: Shells
Requires-Python: >=3.9
